huango/__init__.py
huango/huango_v2.0/README.md
huango/huango_v2.0/huango_v2.0_二进制.7z
huango/huango_v2.0/license.txt
huango-2025.12.9.dist-info/WHEEL
huango-2025.12.9.dist-info/METADATA
huango-2025.12.9.dist-info/RECORD
