Metadata-Version: 2.4
Name: huango
Version: 2025.12.9
Summary: Huango 是一款面向个人卖家、小型商户打造的免费开源独立商城系统，无需复杂部署、无功能限制、无付费门槛，可快速搭建专属的独立电商阵地，覆盖商品展示、买家咨询、在线答疑、自动回复、流量统计全核心流程，助力中小商家低成本实现线上经营。
Author-email: 许灿标 <canbiaoxu@outlook.com>
Requires-Python: >=3.12
